{
  "cars": [
    {
      "id": "40930288",
      "brand": "제네시스",
      "model": "GV80 2.5T 가솔린 AWD",
      "year": 202008,
      "mileage": "61,456 km",
      "price": "4880 만원",
      "priceValue": 4880,
      "photo": "https://ci.encar.com/carpicture/carpicture01/pic4091/40917285_001.jpg",
      "category": "Sedan"
    },
    {
      "id": "41056630",
      "brand": "현대",
      "model": "더 뉴 투싼 (NX4) 가솔린 1.6 터보 2WD",
      "year": 202405,
      "mileage": "15,492 km",
      "price": "3080 만원",
      "priceValue": 3080,
      "photo": "https://ci.encar.com/carpicture/carpicture05/pic4105/41056373_001.jpg",
      "category": "Sedan"
    },
    {
      "id": "41671376",
      "brand": "기아",
      "model": "더 뉴 기아 레이 프레스티지",
      "year": 202212,
      "mileage": "24,713 km",
      "price": "1520 만원",
      "priceValue": 1520,
      "photo": "https://ci.encar.com/carpicture/carpicture06/pic4166/41664648_001.jpg",
      "category": "Sedan"
    },
    {
      "id": "41680275",
      "brand": "KG모빌리티(쌍용)",
      "model": "토레스 가솔린 1.5 2WD",
      "year": 202303,
      "mileage": "46,402 km",
      "price": "2280 만원",
      "priceValue": 2280,
      "photo": "https://ci.encar.com/carpicture/carpicture07/pic4167/41679962_001.jpg",
      "category": "Sedan"
    },
    {
      "id": "41166504",
      "brand": "기아",
      "model": "K5 3세대 1.6 터보",
      "year": 202003,
      "mileage": "60,366 km",
      "price": "2280 만원",
      "priceValue": 2280,
      "photo": "https://ci.encar.com/carpicture/carpicture06/pic4116/41164330_001.jpg",
      "category": "Sedan"
    },
    {
      "id": "41700881",
      "brand": "기아",
      "model": "더 뉴 기아 레이 시그니처",
      "year": 202311,
      "mileage": "6,563 km",
      "price": "1820 만원",
      "priceValue": 1820,
      "photo": "https://ci.encar.com/carpicture/carpicture09/pic4169/41695195_001.jpg",
      "category": "Sedan"
    },
    {
      "id": "41611473",
      "brand": "기아",
      "model": "더 뉴 모닝 (JA) 시그니처",
      "year": 202410,
      "mileage": "20,663 km",
      "price": "1780 만원",
      "priceValue": 1780,
      "photo": "https://ci.encar.com/carpicture/carpicture10/pic4160/41606649_001.jpg",
      "category": "Sedan"
    },
    {
      "id": "41300510",
      "brand": "기아",
      "model": "더 뉴 모하비 디젤 3.0 4WD",
      "year": 201606,
      "mileage": "168,466 km",
      "price": "1480 만원",
      "priceValue": 1480,
      "photo": "https://ci.encar.com/carpicture/carpicture09/pic4129/41299120_001.jpg",
      "category": "Sedan"
    },
    {
      "id": "41723214",
      "brand": "기아",
      "model": "올 뉴 모닝 (JA) 프레스티지",
      "year": 201707,
      "mileage": "64,477 km",
      "price": "850 만원",
      "priceValue": 850,
      "photo": "https://ci.encar.com/carpicture/carpicture02/pic4172/41722273_001.jpg",
      "category": "Sedan"
    },
    {
      "id": "41444729",
      "brand": "기아",
      "model": "레이 프레스티지",
      "year": 201305,
      "mileage": "115,512 km",
      "price": "730 만원",
      "priceValue": 730,
      "photo": "https://ci.encar.com/carpicture/carpicture04/pic4144/41443332_001.jpg",
      "category": "Sedan"
    },
    {
      "id": "41737293",
      "brand": "BMW",
      "model": "5시리즈 (G30) 530i M 스포츠",
      "year": 201712,
      "mileage": "108,501 km",
      "price": "2430 만원",
      "priceValue": 2430,
      "photo": "https://ci.encar.com/carpicture/carpicture03/pic4173/41733828_001.jpg",
      "category": "Sedan"
    },
    {
      "id": "41756035",
      "brand": "BMW",
      "model": "5시리즈 (G30) 530i M 스포츠 플러스",
      "year": 201801,
      "mileage": "74,169 km",
      "price": "2850 만원",
      "priceValue": 2850,
      "photo": "https://ci.encar.com/carpicture/carpicture05/pic4175/41753995_001.jpg",
      "category": "Sedan"
    },
    {
      "id": "41444425",
      "brand": "기아",
      "model": "더 뉴 쏘렌토 디젤 2.0 2WD",
      "year": 201801,
      "mileage": "143,984 km",
      "price": "1480 만원",
      "priceValue": 1480,
      "photo": "https://ci.encar.com/carpicture/carpicture04/pic4144/41443310_001.jpg",
      "category": "Sedan"
    },
    {
      "id": "41649596",
      "brand": "기아",
      "model": "올 뉴 쏘렌토 디젤 2.0 2WD",
      "year": 201606,
      "mileage": "123,258 km",
      "price": "1580 만원",
      "priceValue": 1580,
      "photo": "https://ci.encar.com/carpicture/carpicture04/pic4164/41649179_001.jpg",
      "category": "Sedan"
    },
    {
      "id": "41644618",
      "brand": "현대",
      "model": "그랜저 (GN7) 2.5 가솔린 2WD",
      "year": 202407,
      "mileage": "51,083 km",
      "price": "3350 만원",
      "priceValue": 3350,
      "photo": "https://ci.encar.com/carpicture/carpicture03/pic4163/41631235_001.jpg",
      "category": "Sedan"
    },
    {
      "id": "41612021",
      "brand": "현대",
      "model": "캐스퍼 디 에센셜",
      "year": 202401,
      "mileage": "38,439 km",
      "price": "1580 만원",
      "priceValue": 1580,
      "photo": "https://ci.encar.com/carpicture/carpicture10/pic4160/41606673_001.jpg",
      "category": "Sedan"
    },
    {
      "id": "41177520",
      "brand": "현대",
      "model": "팰리세이드 디젤 2.2 4WD",
      "year": 202007,
      "mileage": "58,172 km",
      "price": "3980 만원",
      "priceValue": 3980,
      "photo": "https://ci.encar.com/carpicture/carpicture07/pic4117/41177176_001.jpg",
      "category": "Sedan"
    },
    {
      "id": "41694955",
      "brand": "현대",
      "model": "더 뉴 아반떼 (CN7) 1.6",
      "year": 202406,
      "mileage": "20,790 km",
      "price": "2550 만원",
      "priceValue": 2550,
      "photo": "https://ci.encar.com/carpicture/carpicture09/pic4169/41692734_001.jpg",
      "category": "Sedan"
    },
    {
      "id": "41246159",
      "brand": "현대",
      "model": "그랜저 IG 2.4 프리미엄",
      "year": 201910,
      "mileage": "22,480 km",
      "price": "1980 만원",
      "priceValue": 1980,
      "photo": "https://ci.encar.com/carpicture/carpicture04/pic4124/41245784_001.jpg",
      "category": "Sedan"
    },
    {
      "id": "41787063",
      "brand": "현대",
      "model": "투싼 하이브리드 (NX4) 인스퍼레이션 2WD",
      "year": 202307,
      "mileage": "25,629 km",
      "price": "3300 만원",
      "priceValue": 3300,
      "photo": "https://ci.encar.com/carpicture/carpicture08/pic4178/41784323_001.jpg",
      "category": "Sedan"
    },
    {
      "id": "41762074",
      "brand": "기아",
      "model": "스팅어 2.0 터보 2WD",
      "year": 201802,
      "mileage": "135,230 km",
      "price": "1580 만원",
      "priceValue": 1580,
      "photo": "https://ci.encar.com/carpicture/carpicture05/pic4175/41757833_001.jpg",
      "category": "Sedan"
    },
    {
      "id": "41319133",
      "brand": "포르쉐",
      "model": "718 카이맨 2.0",
      "year": 201912,
      "mileage": "36,742 km",
      "price": "6290 만원",
      "priceValue": 6290,
      "photo": "https://ci.encar.com/carpicture/carpicture10/pic4130/41302817_001.jpg",
      "category": "Sedan"
    },
    {
      "id": "41616112",
      "brand": "포르쉐",
      "model": "718 카이맨 2.0",
      "year": 201902,
      "mileage": "75,399 km",
      "price": "5890 만원",
      "priceValue": 5890,
      "photo": "https://ci.encar.com/carpicture/carpicture10/pic4160/41604738_001.jpg",
      "category": "Sedan"
    },
    {
      "id": "40933888",
      "brand": "BMW",
      "model": "M2 (G87) M2 쿠페",
      "year": 202309,
      "mileage": "56,779 km",
      "price": "6790 만원",
      "priceValue": 6790,
      "photo": "https://ci.encar.com/carpicture/carpicture02/pic4092/40922537_001.jpg",
      "category": "Sedan"
    },
    {
      "id": "41159854",
      "brand": "제네시스",
      "model": "GV70 2.5T 가솔린 AWD",
      "year": 202304,
      "mileage": "47,408 km",
      "price": "4550 만원",
      "priceValue": 4550,
      "photo": "https://ci.encar.com/carpicture/carpicture04/pic4114/41145710_001.jpg",
      "category": "Sedan"
    },
    {
      "id": "41315276",
      "brand": "폭스바겐",
      "model": "뉴 제타 2.0 TDI 블루모션 프리미엄",
      "year": 201510,
      "mileage": "135,164 km",
      "price": "670 만원",
      "priceValue": 670,
      "photo": "https://ci.encar.com/carpicture/carpicture10/pic4110/41108028_001.jpg",
      "category": "Sedan"
    },
    {
      "id": "41315277",
      "brand": "기아",
      "model": "올 뉴 카니발 9인승 프레스티지",
      "year": 201505,
      "mileage": "191,160 km",
      "price": "850 만원",
      "priceValue": 850,
      "photo": "https://ci.encar.com/carpicture/carpicture05/pic4125/41250724_001.jpg",
      "category": "Sedan"
    },
    {
      "id": "41433340",
      "brand": "기아",
      "model": "쏘렌토 4세대 디젤 2.2 2WD",
      "year": 202101,
      "mileage": "82,121 km",
      "price": "2370 만원",
      "priceValue": 2370,
      "photo": "https://ci.encar.com/carpicture/carpicture03/pic4143/41431248_001.jpg",
      "category": "Sedan"
    },
    {
      "id": "41344924",
      "brand": "벤츠",
      "model": "GLC-클래스 X253 GLC300e 4MATIC",
      "year": 202109,
      "mileage": "39,009 km",
      "price": "4350 만원",
      "priceValue": 4350,
      "photo": "https://ci.encar.com/carpicture/carpicture04/pic4134/41340721_001.jpg",
      "category": "Sedan"
    },
    {
      "id": "41359046",
      "brand": "기아",
      "model": "카니발 4세대 9인승 프레스티지",
      "year": 202205,
      "mileage": "97,598 km",
      "price": "2550 만원",
      "priceValue": 2550,
      "photo": "https://ci.encar.com/carpicture/carpicture05/pic4135/41357256_001.jpg",
      "category": "Sedan"
    },
    {
      "id": "40929709",
      "brand": "기아",
      "model": "쏘렌토 4세대 HEV 1.6 2WD",
      "year": 202101,
      "mileage": "29,220 km",
      "price": "2990 만원",
      "priceValue": 2990,
      "photo": "https://ci.encar.com/carpicture/carpicture02/pic4092/40924400_001.jpg",
      "category": "Sedan"
    },
    {
      "id": "41071482",
      "brand": "BMW",
      "model": "X5 (G05) xDrive 45e xLine",
      "year": 202110,
      "mileage": "38,952 km",
      "price": "6990 만원",
      "priceValue": 6990,
      "photo": "https://ci.encar.com/carpicture/carpicture07/pic4107/41071206_001.jpg",
      "category": "Sedan"
    },
    {
      "id": "41188466",
      "brand": "아우디",
      "model": "A6 (C8) 45 TFSI 콰트로 프리미엄",
      "year": 202207,
      "mileage": "57,213 km",
      "price": "4200 만원",
      "priceValue": 4200,
      "photo": "https://ci.encar.com/carpicture/carpicture07/pic4117/41179258_001.jpg",
      "category": "Sedan"
    },
    {
      "id": "40820928",
      "brand": "제네시스",
      "model": "GV60 스탠다드",
      "year": 202204,
      "mileage": "81,265 km",
      "price": "4180 만원",
      "priceValue": 4180,
      "photo": "https://ci.encar.com/carpicture/carpicture01/pic4081/40816176_001.jpg",
      "category": "Sedan"
    },
    {
      "id": "40963192",
      "brand": "BMW",
      "model": "X3 (G01) xDrive 20i M 스포츠",
      "year": 202209,
      "mileage": "39,458 km",
      "price": "5120 만원",
      "priceValue": 5120,
      "photo": "https://ci.encar.com/carpicture/carpicture05/pic4095/40955587_001.jpg",
      "category": "Sedan"
    },
    {
      "id": "41440665",
      "brand": "BMW",
      "model": "X7 (G07) xDrive 40i M 스포츠 6인승",
      "year": 202105,
      "mileage": "29,986 km",
      "price": "9460 만원",
      "priceValue": 9460,
      "photo": "https://ci.encar.com/carpicture/carpicture03/pic4143/41439386_001.jpg",
      "category": "Sedan"
    },
    {
      "id": "41319107",
      "brand": "BMW",
      "model": "X7 (G07) xDrive 40i M 스포츠 6인승",
      "year": 202206,
      "mileage": "43,353 km",
      "price": "8950 만원",
      "priceValue": 8950,
      "photo": "https://ci.encar.com/carpicture/carpicture01/pic4131/41312941_001.jpg",
      "category": "Sedan"
    },
    {
      "id": "41554495",
      "brand": "쉐보레(GM대우)",
      "model": "리얼 뉴 콜로라도 3.6 익스트림-X 4WD",
      "year": 202108,
      "mileage": "58,816 km",
      "price": "2480 만원",
      "priceValue": 2480,
      "photo": "https://ci.encar.com/carpicture/carpicture05/pic4155/41553903_001.jpg",
      "category": "Sedan"
    },
    {
      "id": "40615934",
      "brand": "BMW",
      "model": "5시리즈 (G30) 520i M 스포츠",
      "year": 202010,
      "mileage": "53,654 km",
      "price": "3990 만원",
      "priceValue": 3990,
      "photo": "https://ci.encar.com/carpicture/carpicture01/pic4061/40612261_001.jpg",
      "category": "Sedan"
    },
    {
      "id": "41532085",
      "brand": "BMW",
      "model": "5시리즈 (G30) M550i xDrive",
      "year": 202102,
      "mileage": "93,776 km",
      "price": "4910 만원",
      "priceValue": 4910,
      "photo": "https://ci.encar.com/carpicture/carpicture02/pic4152/41529256_001.jpg",
      "category": "Sedan"
    }
  ],
  "lastUpdated": "2026-04-02T06:35:27.369Z"
}